wikitables/__init__.py
wikitables/cli.py
wikitables/client.py
wikitables/models.py
wikitables/readers.py
wikitables/templates.py
wikitables/util.py
wikitables/version.py
wikitables-0.5.5.dist-info/LICENSE
wikitables-0.5.5.dist-info/METADATA
wikitables-0.5.5.dist-info/WHEEL
wikitables-0.5.5.dist-info/entry_points.txt
wikitables-0.5.5.dist-info/top_level.txt
wikitables-0.5.5.dist-info/RECORD
