Metadata-Version: 2.1
Name: wikitables
Version: 0.5.5
Summary: Import tables from any Wikipedia article
Home-page: https://github.com/bcicen/wikitables
Author: Bradley Cicenas
Author-email: bradley@vektor.nyc
License: http://opensource.org/licenses/MIT
Keywords: wikipedia data cli commandline
Platform: UNKNOWN
Classifier: Natural Language :: English
Classifier: Programming Language :: Python
Classifier: Intended Audience :: Developers
Classifier: Programming Language :: Python :: 2
Classifier: Programming Language :: Python :: 3
Classifier: License :: OSI Approved :: MIT License
License-File: LICENSE
Requires-Dist: mwparserfromhell (>=0.4.3)
Requires-Dist: requests (>=2.9.1)
Requires-Dist: pycountry (>=20.7.3)
